utilityhelper/HelperConfigParser.py
utilityhelper/HelperMultiThread.py
utilityhelper/LogUtil.py
utilityhelper/__init__.py
utilityhelper/__version__.py
utilityhelper/compatible.py
utilityhelper/loggingHelper.py
utilityhelper/common/HelperDecorator.py
utilityhelper/common/HelperMagic.py
utilityhelper/common/__init__.py
utilityhelper/common/util/BasicUtil.py
utilityhelper/common/util/DBUtil.py
utilityhelper/common/util/DESUtil.py
utilityhelper/common/util/__init__.py
utilityhelper/common/util/CertUil/__init__.py
utilityhelper/common/util/CertUil/cert.py
utilityhelper/common/util/crc/__init__.py
utilityhelper/common/util/crc/crc-itu.py
utilityhelper/helperserial/__init__.py
utilityhelper/helperserial/serial_port_manager.py
utilityhelper/helperserial/serial_reader_observer.py
utilityhelper/serial27/__init__.py
utilityhelper/serial27/rfc2217.py
utilityhelper/serial27/serialcli.py
utilityhelper/serial27/serialjava.py
utilityhelper/serial27/serialposix.py
utilityhelper/serial27/serialutil.py
utilityhelper/serial27/serialwin32.py
utilityhelper/serial27/sermsdos.py
utilityhelper/serial27/win32.py
utilityhelper/serial27/tools/__init__.py
utilityhelper/serial27/tools/list_ports.py
utilityhelper/serial27/tools/list_ports_linux.py
utilityhelper/serial27/tools/list_ports_osx.py
utilityhelper/serial27/tools/list_ports_posix.py
utilityhelper/serial27/tools/list_ports_windows.py
utilityhelper/serial27/tools/miniterm.py
utilityhelper/serial27/urlhandler/__init__.py
utilityhelper/serial27/urlhandler/protocol_hwgrep.py
utilityhelper/serial27/urlhandler/protocol_loop.py
utilityhelper/serial27/urlhandler/protocol_rfc2217.py
utilityhelper/serial27/urlhandler/protocol_socket.py
utilityhelper/test/__init__.py
utilityhelper/test/loggingHelperDemo.py
utilityhelper/test/testGrid.py
utilityhelper/util/Observer.py
utilityhelper/util/Synchronization.py
utilityhelper/util/__init__.py
utilityhelper/util/ascbin.py
utilityhelper/wxwrap/HelpGridTable.py
utilityhelper/wxwrap/HelperButton.py
utilityhelper-0.1.10.dist-info/LICENSE.txt
utilityhelper-0.1.10.dist-info/METADATA
utilityhelper-0.1.10.dist-info/WHEEL
utilityhelper-0.1.10.dist-info/top_level.txt
utilityhelper-0.1.10.dist-info/RECORD
